xeno/__init__.py
xeno/client.py
xeno/exceptions.py
xeno/_types/__init__.py
xeno/_types/responses.py
xeno/resources/__init__.py
xeno/resources/chat.py
xeno/resources/image.py
xeno/resources/models.py
xeno/resources/music.py
xeno/resources/video.py
xeno_ai-0.1.0.dist-info/METADATA
xeno_ai-0.1.0.dist-info/WHEEL
xeno_ai-0.1.0.dist-info/top_level.txt
xeno_ai-0.1.0.dist-info/RECORD
