Metadata-Version: 2.4
Name: xeno-ai
Version: 0.1.0
Summary: Official Python SDK for Xeno API - Access 100+ AI models for image, video, music, and text generation
Author-email: Xeno Studio <support@xeno-studio.com>
License: MIT
Project-URL: Homepage, https://xeno-studio.com
Project-URL: Documentation, https://xeno-studio.com/docs
Project-URL: Repository, https://github.com/xeno-studio/xeno-python
Keywords: ai,api,image-generation,video-generation,music-generation,llm,flux,openai,anthropic
Classifier: Development Status :: 4 - Beta
Classifier: Intended Audience :: Developers
Classifier: License :: OSI Approved :: MIT License
Classifier: Programming Language :: Python :: 3
Classifier: Programming Language :: Python :: 3.8
Classifier: Programming Language :: Python :: 3.9
Classifier: Programming Language :: Python :: 3.10
Classifier: Programming Language :: Python :: 3.11
Classifier: Programming Language :: Python :: 3.12
Classifier: Topic :: Scientific/Engineering :: Artificial Intelligence
Requires-Python: >=3.8
Requires-Dist: httpx>=0.24.0
Requires-Dist: pydantic>=2.0.0
Requires-Dist: typing-extensions>=4.0.0
Provides-Extra: dev
Requires-Dist: pytest>=7.0.0; extra == "dev"
Requires-Dist: pytest-asyncio>=0.21.0; extra == "dev"
Requires-Dist: black>=23.0.0; extra == "dev"
Requires-Dist: mypy>=1.0.0; extra == "dev"
Requires-Dist: ruff>=0.1.0; extra == "dev"
